core/__init__.py
core/app/__init__.py
core/app/app_controller.py
core/app/app_event.py
core/app/app_module.py
core/app/app_processor.py
core/app/data.py
core/app/http_exception_handler.py
core/dal/__init__.py
core/dal/data.py
core/dal/database_errors.py
core/dal/postgres_connection.py
core/dal/postgres_repository.py
core/di/__init__.py
core/di/injector.py
core/di/injector_manager.py
core/files/__init__.py
core/files/file_storage.py
core/msq/__init__.py
core/msq/msg_queue.py
core/rules_engine/__init__.py
core/rules_engine/data.py
core/rules_engine/exceptions.py
core/rules_engine/rule_manager.py
core/utils/__init__.py
core/utils/convert.py
core/utils/data.py
braincube_aws_core-0.0.29.dist-info/LICENSE
braincube_aws_core-0.0.29.dist-info/METADATA
braincube_aws_core-0.0.29.dist-info/WHEEL
braincube_aws_core-0.0.29.dist-info/top_level.txt
braincube_aws_core-0.0.29.dist-info/RECORD
