Metadata-Version: 2.1
Name: braincube-aws-core
Version: 0.0.29
Summary: Microframework for python aws lambdas
Home-page: https://bitbucket.org/braincube-common/core-aws.git
Author: Braincube
Author-email: v.boudis@braincube.gr
License: MIT
Keywords: python,amazon,aws,lambda,routing,dal,injection
Classifier: Intended Audience :: Developers
Classifier: License :: OSI Approved :: MIT License
Classifier: Operating System :: OS Independent
Classifier: Programming Language :: Python
Classifier: Programming Language :: Python :: 3.10
Classifier: Programming Language :: Python :: 3.11
Classifier: Topic :: Software Development :: Libraries :: Python Modules
Requires-Python: <4,>=3.10
License-File: LICENSE
Requires-Dist: asyncpg ==0.27.0
Requires-Dist: pypika ==0.48.9
Requires-Dist: pydantic ==1.10.7
Requires-Dist: boto3 ==1.28.34
Requires-Dist: rule-engine ==3.5.1
